setup.py
marvin/__init__.py
marvin/abstractwf.py
marvin/concretewf.py
marvin/inputdata_xml.py
marvin/iteration.py
marvin/main.py
marvin/workflow_xml.py
marvin_wfms.egg-info/PKG-INFO
marvin_wfms.egg-info/SOURCES.txt
marvin_wfms.egg-info/dependency_links.txt
marvin_wfms.egg-info/top_level.txt