Metadata-Version: 1.1
Name: marvin-wfms
Version: 0.0.1
Summary: Pilot-based GWENDIA Workflow Enacter.
Home-page: http://packages.python.org/marvin_wfms
Author: Mark Santcroos
Author-email: mark.santcroos@rutgers.edu
License: BSD
Keywords: workflow gwendia pilot
Platform: UNKNOWN
Classifier: Development Status :: 3 - Alpha
Classifier: Programming Language :: Python
Classifier: Topic :: Utilities
Classifier: License :: OSI Approved :: BSD License
